__init__.py
para_walk.py
para_walk-1.0.0.dist-info/LICENSE
para_walk-1.0.0.dist-info/METADATA
para_walk-1.0.0.dist-info/WHEEL
para_walk-1.0.0.dist-info/top_level.txt
para_walk-1.0.0.dist-info/RECORD
