Metadata-Version: 2.1
Name: para-walk
Version: 1.0.0
Summary: a simple parallel version of os.walk
Author-email: Shiqi Yang <yangshiqi@mail.cbi.pku.edu.cn>
License: Apache License
Project-URL: Homepage, https://github.com/shiqi-yang/para_walk
Keywords: parallel,walk
Classifier: License :: OSI Approved :: Apache Software License
Classifier: Programming Language :: Python
Classifier: Programming Language :: Python :: 3
Requires-Python: >=3.5
License-File: LICENSE
Requires-Dist: tqdm
